derpy/__init__.py
derpy/bond.py
derpy/bond_calcs.py
derpy/cli.py
derpy/derpy.py
derpy/option.py
derpy/option_binomial.py
derpy/option_bsm.py
derpy/portfolio.py
derpy-0.1.1.dist-info/DESCRIPTION.rst
derpy-0.1.1.dist-info/METADATA
derpy-0.1.1.dist-info/RECORD
derpy-0.1.1.dist-info/WHEEL
derpy-0.1.1.dist-info/entry_points.txt
derpy-0.1.1.dist-info/metadata.json
derpy-0.1.1.dist-info/top_level.txt
derpy-0.1.1.dist-info/zip-safe
