Metadata-Version: 2.0
Name: derpy
Version: 0.1.1
Summary: Financial derivatives and portfolio analysis tools for python
Home-page: https://github.com/rjdscott/derpy
Author: Rob Scott
Author-email: rob@rjdscott.com
License: MIT license
Keywords: derpy asset stock exchange securities market finance investment money currency cost framework
Platform: UNKNOWN
Classifier: Development Status :: 2 - Pre-Alpha
Classifier: Intended Audience :: Developers
Classifier: License :: OSI Approved :: MIT License
Classifier: Natural Language :: English
Classifier: Programming Language :: Python :: 2
Classifier: Programming Language :: Python :: 2.7
Classifier: Programming Language :: Python :: 3
Classifier: Programming Language :: Python :: 3.4
Classifier: Programming Language :: Python :: 3.5
Classifier: Programming Language :: Python :: 3.6
Requires-Dist: Click (>=6.0)
Requires-Dist: pandas
Requires-Dist: numpy
Requires-Dist: scipy
